aquaref/__init__.py
aquaref/basic.py
aquaref/library/__init__.py
aquaref/library/metro/net40/MetroFramework.Design.dll
aquaref/library/metro/net40/MetroFramework.dll
aquaref/library/metro/net40/MetroFramework.Fonts.dll
aquaref/library/metro.py
aquaref/library/realtaiizor/net60-windows7/ReaLTaiizor.dll
aquaref/library/realtaiizor/net60-windows7/ReaLTaiizor.xml
aquaref/library/realtaiizor.py
aquaref/test.1.py
aquaref/test.metro.1.log
aquaref/test.metro.1.py
aquaref/test.realtaiizor.1.py
aquaref/winforms/__init__.py
aquaref/winforms/application.py
aquaref/winforms/button.py
aquaref/winforms/control.py
aquaref/winforms/form.py
aquaref/winforms/label.py
aquaref/winforms/metro/__init__.py
aquaref/winforms/metro/metro_animationbase.py
aquaref/winforms/metro/metro_button.py
aquaref/winforms/metro/metro_color_style.txt
aquaref/winforms/metro/metro_control.py
aquaref/winforms/metro/metro_form.py
aquaref/winforms/metro/metro_form.txt
aquaref/winforms/metro/metro_label.py
aquaref/winforms/metro/metro_messagebox.py
aquaref/winforms/metro/metro_panel.py
aquaref/winforms/metro/metro_style_manager.py
aquaref/winforms/metro/metro_style_manager.txt
aquaref/winforms/metro/metro_tab_control.py
aquaref/winforms/metro/metro_tab_page.py
aquaref/winforms/metro/metro_tooltip.py
aquaref/winforms/py.ico
aquaref/winforms/realtaiizor/__init__.py
aquaref/winforms/tooltip.py
aquaref/wpf/__init__.py
aquaref/wpf/code.py
aquaref/wpf/gui.xaml
aquaref/wpf/thread.py
aquaref/wpf/window.py
aquaref_full-0.0.1a1.dist-info/METADATA
aquaref_full-0.0.1a1.dist-info/WHEEL
aquaref_full-0.0.1a1.dist-info/RECORD
